allreverso/__init__.py
allreverso/__version__.py
allreverso/result.py
allreverso-1.2.7.dist-info/LICENSE
allreverso-1.2.7.dist-info/METADATA
allreverso-1.2.7.dist-info/WHEEL
allreverso-1.2.7.dist-info/top_level.txt
allreverso-1.2.7.dist-info/RECORD
