Metadata-Version: 2.1
Name: allreverso
Version: 1.2.7
Summary: A simple package to handle allreverso.net services (translation, voice, dictionary etc.).
Home-page: UNKNOWN
Author: PetitPotiron
License: Apache 2.0
Project-URL: Homepage, https://github.com/PetitPotiron/allreverso
Platform: UNKNOWN
Classifier: Development Status :: 5 - Production/Stable
Classifier: Topic :: Internet :: WWW/HTTP
Classifier: Topic :: Internet :: WWW/HTTP :: Site Management :: Link Checking
Classifier: Environment :: Console
Classifier: Environment :: Web Environment
Classifier: Intended Audience :: Developers
Classifier: Programming Language :: Python :: 3.5
Classifier: Programming Language :: Python :: 3.6
Classifier: Programming Language :: Python :: 3.7
Classifier: Programming Language :: Python :: 3.8
Classifier: License :: OSI Approved :: Apache Software License
Classifier: Operating System :: OS Independent
Requires-Dist: requests
Requires-Dist: bs4
Requires-Dist: lxml
